polypuppet/__init__.py
polypuppet/agent/__init__.py
polypuppet/agent/agent.py
polypuppet/agent/cli.py
polypuppet/agent/output.py
polypuppet/agent/pc.py
polypuppet/agent/vagrant.py
polypuppet/config.py
polypuppet/definitions.py
polypuppet/exception.py
polypuppet/messages.py
polypuppet/polypuppet_pb2.py
polypuppet/polypuppet_pb2_grpc.py
polypuppet/puppet.py
polypuppet/server/__init__.py
polypuppet/server/authentication.py
polypuppet/server/cert_list.py
polypuppet/server/classroom.py
polypuppet/server/person.py
polypuppet/server/server.py
polypuppet/server/token.py
polypuppet-0.1.7.dist-info/entry_points.txt
polypuppet-0.1.7.dist-info/LICENSE
polypuppet-0.1.7.dist-info/WHEEL
polypuppet-0.1.7.dist-info/METADATA
polypuppet-0.1.7.dist-info/RECORD
