Metadata-Version: 2.1
Name: polypuppet
Version: 0.1.7
Summary: Administration tool for SPBSTU
License: MIT
Author: LLDay
Author-email: ssdenis99@gmail.com
Requires-Python: >=3.6,<4.0
Classifier: License :: OSI Approved :: MIT License
Classifier: Programming Language :: Python :: 3
Classifier: Programming Language :: Python :: 3.6
Classifier: Programming Language :: Python :: 3.7
Classifier: Programming Language :: Python :: 3.8
Classifier: Programming Language :: Python :: 3.9
Requires-Dist: click (>=7.1.2,<8.0.0)
Requires-Dist: colorama (>=0.4.4,<0.5.0)
Requires-Dist: configparser (>=5.0.2,<6.0.0)
Requires-Dist: distro (>=1.5.0,<2.0.0)
Requires-Dist: grpcio (>=1.38.0,<2.0.0)
Requires-Dist: protobuf (>=3.15.7,<4.0.0)
Requires-Dist: python-vagrant (>=0.5.15,<0.6.0)
Requires-Dist: requests-html (>=0.10.0,<0.11.0)
Requires-Dist: systemd-python (>=234,<235); sys_platform == "linux"
